rfcs/__init__.py
rfcs/rfcs.py
rfcs-1.0.1.dist-info/DESCRIPTION.rst
rfcs-1.0.1.dist-info/METADATA
rfcs-1.0.1.dist-info/RECORD
rfcs-1.0.1.dist-info/WHEEL
rfcs-1.0.1.dist-info/entry_points.txt
rfcs-1.0.1.dist-info/metadata.json
rfcs-1.0.1.dist-info/top_level.txt
