Metadata-Version: 2.0
Name: rfcs
Version: 1.0.1
Summary: rfcs is the complete command-line tool to search and view RFCs.
Home-page: http://github.com/lukedmor/rfcs
Author: Lucas Morales
Author-email: lucas@lucasem.com
License: GNU GPL v2.0
Keywords: rfc internet networking protocol concept notes command command-line cli
Platform: UNKNOWN
Classifier: Development Status :: 4 - Beta
Classifier: Intended Audience :: Developers
Classifier: Intended Audience :: Science/Research
Classifier: Intended Audience :: Telecommunications Industry
Classifier: Topic :: Communications
Classifier: Topic :: Documentation
Classifier: Topic :: Internet
Classifier: Topic :: Scientific/Engineering :: Interface Engine/Protocol Translator
Classifier: Topic :: Security
Classifier: Topic :: Software Development
Classifier: Topic :: Software Development :: Documentation
Classifier: Topic :: Utilities
Classifier: License :: OSI Approved :: GNU General Public License v2 (GPLv2)
Classifier: Programming Language :: Python :: 3
Classifier: Programming Language :: Python :: 3.2
Classifier: Programming Language :: Python :: 3.3
Classifier: Programming Language :: Python :: 3.4
Classifier: Programming Language :: Python :: 3.5
Requires-Dist: beautifulsoup4
Requires-Dist: requests
